MeteorZhongwenWendang/README.md
MeteorZhongwenWendang/__init__.py
MeteorZhongwenWendang/__main__.py
MeteorZhongwenWendang/file.epub
MeteorZhongwenWendang/index.html
MeteorZhongwenWendang/css/__init__.py
MeteorZhongwenWendang/css/annotations.css
MeteorZhongwenWendang/css/main.css
MeteorZhongwenWendang/css/normalize.css
MeteorZhongwenWendang/css/popup.css
MeteorZhongwenWendang/font/__init__.py
MeteorZhongwenWendang/font/fontello.eot
MeteorZhongwenWendang/font/fontello.svg
MeteorZhongwenWendang/font/fontello.ttf
MeteorZhongwenWendang/font/fontello.woff
MeteorZhongwenWendang/img/__init__.py
MeteorZhongwenWendang/img/annotator-glyph-sprite.png
MeteorZhongwenWendang/img/annotator-icon-sprite.png
MeteorZhongwenWendang/img/apple-touch-icon.png
MeteorZhongwenWendang/img/cancelfullscreen.png
MeteorZhongwenWendang/img/close.png
MeteorZhongwenWendang/img/fullscreen.png
MeteorZhongwenWendang/img/loader.gif
MeteorZhongwenWendang/img/menu-icon.png
MeteorZhongwenWendang/img/save.png
MeteorZhongwenWendang/img/saved.png
MeteorZhongwenWendang/img/settings-s.png
MeteorZhongwenWendang/img/settings.png
MeteorZhongwenWendang/img/star.png
MeteorZhongwenWendang/js/__init__.py
MeteorZhongwenWendang/js/epub.js
MeteorZhongwenWendang/js/epub.min.js
MeteorZhongwenWendang/js/epub.min.map
MeteorZhongwenWendang/js/hooks.min.js
MeteorZhongwenWendang/js/hooks.min.map
MeteorZhongwenWendang/js/reader.js
MeteorZhongwenWendang/js/reader.js.map
MeteorZhongwenWendang/js/reader.min.js
MeteorZhongwenWendang/js/reader.min.map
MeteorZhongwenWendang/js/hooks/__init__.py
MeteorZhongwenWendang/js/hooks/extensions/__init__.py
MeteorZhongwenWendang/js/hooks/extensions/highlight.js
MeteorZhongwenWendang/js/libs/__init__.py
MeteorZhongwenWendang/js/libs/jquery.min.js
MeteorZhongwenWendang/js/libs/localforage.min.js
MeteorZhongwenWendang/js/libs/screenfull.js
MeteorZhongwenWendang/js/libs/screenfull.min.js
MeteorZhongwenWendang/js/libs/zip.min.js
MeteorZhongwenWendang/js/plugins/__init__.py
meteor_zhongwen_wendang-2024.2.29.0.dist-info/METADATA
meteor_zhongwen_wendang-2024.2.29.0.dist-info/WHEEL
meteor_zhongwen_wendang-2024.2.29.0.dist-info/entry_points.txt
meteor_zhongwen_wendang-2024.2.29.0.dist-info/top_level.txt
meteor_zhongwen_wendang-2024.2.29.0.dist-info/RECORD
